mindtrace/registry/__init__.py
mindtrace/registry/archivers/__init__.py
mindtrace/registry/archivers/config_archiver.py
mindtrace/registry/archivers/default_archivers.py
mindtrace/registry/archivers/path_archiver.py
mindtrace/registry/archivers/ultralytics/sam_archiver.py
mindtrace/registry/archivers/ultralytics/yolo_archiver.py
mindtrace/registry/archivers/ultralytics/yoloe_archiver.py
mindtrace/registry/backends/__init__.py
mindtrace/registry/backends/gcp_registry_backend.py
mindtrace/registry/backends/local_registry_backend.py
mindtrace/registry/backends/minio_registry_backend.py
mindtrace/registry/backends/registry_backend.py
mindtrace/registry/core/__init__.py
mindtrace/registry/core/archiver.py
mindtrace/registry/core/exceptions.py
mindtrace/registry/core/registry.py
mindtrace_registry-0.8.0.dist-info/licenses/LICENSE
mindtrace_registry-0.8.0.dist-info/METADATA
mindtrace_registry-0.8.0.dist-info/WHEEL
mindtrace_registry-0.8.0.dist-info/top_level.txt
mindtrace_registry-0.8.0.dist-info/RECORD
