Metadata-Version: 2.4
Name: mindtrace-registry
Version: 0.8.0
Summary: Registry functionality for Mindtrace
Author: Mindtrace Team
License-Expression: Apache-2.0
Project-URL: Homepage, https://mindtrace.ai
Project-URL: Repository, https://github.com/mindtrace/mindtrace/blob/main/mindtrace/registry
Classifier: Programming Language :: Python :: 3
Classifier: Programming Language :: Python :: 3.12
License-File: LICENSE
Requires-Dist: mindtrace-core>=0.8.0
Requires-Dist: mindtrace-storage>=0.8.0
Requires-Dist: minio<7.2.19
Requires-Dist: pydantic>=2.11.1
Requires-Dist: pyyaml>=6.0.1
Requires-Dist: zenml>=0.82.1
Dynamic: license-file
